[{"model": "travel_agency.GradeLevel", "pk": "10010", "fields": {"title": "freshmen", "min_credits": "20", "max_credits": "90"}}, {"model": "travel_agency.GradeLevel", "pk": "10020", "fields": {"title": "sophomore", "min_credits": "20", "max_credits": "90"}}, {"model": "travel_agency.GradeLevel", "pk": "10030", "fields": {"title": "junior", "min_credits": "20", "max_credits": "90"}}, {"model": "travel_agency.GradeLevel", "pk": "10040", "fields": {"title": "senior", "min_credits": "20", "max_credits": "90"}}]